### 对象的创建过程

首先，写一段代码编译一下字节码，参考之前的指令知识来看一下对象创建的过程。

```java
public class Main {
    public static void main(String[] args) {
        Entry entry = new Entry();
    }
}

public class Entry {
    private int total = 10;

    public int getTotal() {
        return total;
    }

    public Entry setTotal(int total) {
        this.total = total;
        return this;
    }
}

```
把上面的代码进行编译、解析

```
fantj@FantJdeMacBook-Pro src % javap -c Main.class 
Compiled from "Main.java"
public class Main {
  public Main();
    Code:
       0: aload_0
       1: invokespecial #1                  // Method java/lang/Object."<init>":()V
       4: return

  public static void main(java.lang.String[]);
    Code:
       0: new           #2                  // class Entry
       3: dup
       4: invokespecial #3                  // Method Entry."<init>":()V
       7: astore_1
       8: return
}

```

#### 字节码解读：
* aload_0: 读取方法的第一个引用参数(或更一般地说,第一个本地引用变量)并将其推送到堆栈.
* invokespecial #1 : 调用Main的super方法，也就是Object的构造方法
* new: 它会接收一个操作数，指向常量池中的一个索引，表示要创建的类型
* dup： 压入栈顶
* invokespecial #3  ：调用Entry的构造方法   （半初始化状态，因为此时的变量还是默认值）
* astore_1：将栈顶值保存到局部变量   （真正初始化完成）